postcash/__init__.py
postcash/smtp.py
postcash-0.1.1.dist-info/WHEEL
postcash-0.1.1.dist-info/METADATA
postcash-0.1.1.dist-info/RECORD
