Metadata-Version: 2.4
Name: postcash
Version: 0.1.1
Summary: Asynchronous Notifications made easy with.
Author-email: "Azat (@azataiot)" <8280770+azataiot@users.noreply.github.com>
Requires-Python: >=3.13
Requires-Dist: pydantic>=2.11.3
Project-URL: Documentation, https://azgh.cc/postcash
Project-URL: Home, https://azgh.cc/postcash/
Project-URL: Homepage, https://azgh.cc/postcash
Project-URL: Repository, https://github.com/azataiot/postcash
